dasha2ui/__init__.py
dasha2ui/core.py
dasha2ui/renderers/__init__.py
dasha2ui/renderers/dash_renderer.py
dasha2ui-0.1.0.dist-info/METADATA
dasha2ui-0.1.0.dist-info/WHEEL
dasha2ui-0.1.0.dist-info/top_level.txt
dasha2ui-0.1.0.dist-info/RECORD
