Metadata-Version: 2.4
Name: dasha2ui
Version: 0.1.0
Summary: A2UI Protocol Implementation for Dash - Declarative UI generation for LLM agents
Author-email: Cemberk <cemberk@example.com>
License: MIT
Project-URL: Homepage, https://github.com/Cemberk/dasha2ui
Project-URL: Repository, https://github.com/Cemberk/dasha2ui.git
Project-URL: Issues, https://github.com/Cemberk/dasha2ui/issues
Keywords: a2ui,dash,plotly,llm,agent,ui,declarative
Classifier: Development Status :: 4 - Beta
Classifier: Intended Audience :: Developers
Classifier: License :: OSI Approved :: MIT License
Classifier: Programming Language :: Python :: 3
Classifier: Programming Language :: Python :: 3.9
Classifier: Programming Language :: Python :: 3.10
Classifier: Programming Language :: Python :: 3.11
Classifier: Programming Language :: Python :: 3.12
Classifier: Topic :: Software Development :: Libraries :: Python Modules
Classifier: Topic :: Scientific/Engineering :: Visualization
Requires-Python: >=3.9
Provides-Extra: dash
Requires-Dist: dash>=2.0.0; extra == "dash"
Requires-Dist: dash-bootstrap-components>=1.0.0; extra == "dash"
Requires-Dist: dash-iconify>=0.1.2; extra == "dash"
Provides-Extra: validation
Requires-Dist: jsonschema>=4.0.0; extra == "validation"
Provides-Extra: all
Requires-Dist: dasha2ui[dash,validation]; extra == "all"
Provides-Extra: dev
Requires-Dist: pytest>=7.0.0; extra == "dev"
Requires-Dist: pytest-cov>=4.0.0; extra == "dev"
Requires-Dist: black>=23.0.0; extra == "dev"
Requires-Dist: ruff>=0.1.0; extra == "dev"
